{
  "GUID": "012d61",
  "Name": "Custom_Model",
  "Transform": {
    "posX": -5.997718,
    "posY": 2.83857727,
    "posZ": -2.39940548,
    "rotX": 0.008273069,
    "rotY": 0.0162015166,
    "rotZ": 0.00855177,
    "scaleX": 1.49999964,
    "scaleY": 1.49999964,
    "scaleZ": 1.49999964
  },
  "Nickname": "$100T",
  "Description": "100 Trillion Dollars",
  "GMNotes": "",
  "AltLookAngle": {
    "x": 0,
    "y": 0,
    "z": 0
  },
  "ColorDiffuse": {
    "r": 0.98999995,
    "g": 1,
    "b": 0.98999995
  },
  "LayoutGroupSortIndex": 0,
  "Value": 0,
  "Locked": false,
  "Grid": true,
  "Snap": true,
  "IgnoreFoW": false,
  "MeasureMovement": false,
  "DragSelectable": true,
  "Autoraise": true,
  "Sticky": true,
  "Tooltip": true,
  "GridProjection": false,
  "HideWhenFaceDown": false,
  "Hands": false,
  "CustomMesh": {
    "MeshURL": "http://cloud-3.steamusercontent.com/ugc/2056504269108415737/DBD1F0B687C6A0E4B735E6034664780907AF83CE/",
    "DiffuseURL": "http://cloud-3.steamusercontent.com/ugc/2508023918742027782/FCBFD21B18BDA6F73D59C8B98F920E347994CE24/",
    "NormalURL": "",
    "ColliderURL": "",
    "Convex": true,
    "MaterialIndex": 1,
    "TypeIndex": 5,
    "CastShadows": true
  }
}